ALTO.py
E.py
E_optimizer_adaptor-0.1.0.dist-info/METADATA
E_optimizer_adaptor-0.1.0.dist-info/WHEEL
E_optimizer_adaptor-0.1.0.dist-info/top_level.txt
E_optimizer_adaptor-0.1.0.dist-info/RECORD
